slackoff/__init__.py
slackoff/__main__.py
slackoff/browser.applescript
slackoff/browser.py
slackoff/cli.py
slackoff/config.py
slackoff/script.py
slackoff/slack.applescript
slackoff/slack.py
slackoff/tests/__init__.py
slackoff/tests/conftest.py
slackoff/tests/test_browser.py
slackoff/tests/test_config.py
slackoff/tests/test_slack.py
slackoff-1.2.dist-info/LICENSE.md
slackoff-1.2.dist-info/METADATA
slackoff-1.2.dist-info/WHEEL
slackoff-1.2.dist-info/entry_points.txt
slackoff-1.2.dist-info/RECORD
