Metadata-Version: 2.1
Name: slackoff
Version: 1.2
Summary: Automatically sign out of Slack workspaces on macOS.
Home-page: https://pypi.org/project/slackoff
License: MIT
Author: Jace Browning
Author-email: jacebrowning@gmail.com
Requires-Python: >=3.10,<4.0
Classifier: Development Status :: 5 - Production/Stable
Classifier: Environment :: Console
Classifier: Intended Audience :: End Users/Desktop
Classifier: License :: OSI Approved :: MIT License
Classifier: Natural Language :: English
Classifier: Operating System :: MacOS
Classifier: Programming Language :: Python
Classifier: Programming Language :: Python :: 3
Classifier: Programming Language :: Python :: 3.10
Classifier: Programming Language :: Python :: 3.11
Classifier: Programming Language :: Python :: 3.12
Classifier: Topic :: Communications :: Chat
Requires-Dist: applescript (>=2021.2.9,<2022.0.0)
Requires-Dist: click (>=8.0,<9.0)
Requires-Dist: datafiles (>=2.2.2,<3.0.0)
Requires-Dist: minilog (>=2.1,<3.0)
Requires-Dist: pync (>=2.0.3,<3.0.0)
Project-URL: Documentation, https://slackoff.readthedocs.io
Project-URL: Repository, https://github.com/jacebrowning/slackoff
